{
  "search_metadata": {
    "id": "66432a55defa134ce756fb47",
    "status": "Success",
    "json_endpoint": "https://serpapi.com/searches/86809de530a25623/66432a55defa134ce756fb47.json",
    "created_at": "2024-05-14 09:09:41 UTC",
    "processed_at": "2024-05-14 09:09:41 UTC",
    "google_url": "https://www.google.com/search?q=inflasi+tasikmalaya&oq=inflasi+tasikmalaya&hl=id&gl=id&num=99999&tbm=nws&sourceid=chrome&ie=UTF-8",
    "raw_html_file": "https://serpapi.com/searches/86809de530a25623/66432a55defa134ce756fb47.html",
    "total_time_taken": 5.48
  },
  "search_parameters": {
    "engine": "google",
    "q": "inflasi tasikmalaya",
    "google_domain": "google.com",
    "hl": "id",
    "gl": "id",
    "num": "99999",
    "device": "desktop",
    "tbm": "nws"
  },
  "search_information": {
    "query_displayed": "inflasi tasikmalaya",
    "total_results": 79,
    "time_taken_displayed": 0.21,
    "news_results_state": "Results for exact spelling"
  },
  "news_results": [
    {
      "position": 1,
      "link": "https://portal.tasikmalayakota.go.id/index.php/q/berita_detail/1163",
      "title": "CAPACITY BUILDING TPID KOTA TASIKMALAYA TAHUN 2024 | Website Resmi Kota Tasikmalaya",
      "source": "Pemerintah Kota Tasikmalaya",
      "date": "4 Jan 2024",
      "snippet": "Tasikmalaya – Kamis 4 Januari 2024 bertempat di Aula Belekota Tasikmalaya dilaksanakan Capacity Building TPID Kota Tasikmalaya Tahun 2024.",
      "thumbnail": "https://serpapi.com/searches/66432a55defa134ce756fb47/images/65153d8e15bd8130004786f64a041c568922d757c4f48b09417c13bdbfec6cb7.jpeg"
    },
    {
      "position": 2,
      "link": "https://www.detik.com/jabar/berita/d-7067936/sukses-kendalikan-inflasi-kota-tasikmalaya-diganjar-penghargaan",
      "title": "Sukses Kendalikan Inflasi, Kota Tasikmalaya Diganjar Penghargaan",
      "source": "Detikcom",
      "date": "2 Des 2023",
      "snippet": "Apresiasi ini diberikan karena pada Oktober 2023 laju inflasi Kota Tasikmalaya sangat rendah, dengan angka 0,01 persen. Atas capaian tersebut...",
      "thumbnail": "https://serpapi.com/searches/66432a55defa134ce756fb47/images/65153d8e15bd813023bd1172824372e4768f4cd79a6e4ed2ba4979f5c5845d62.jpeg"
    },
    {
      "position": 3,
      "link": "https://www.antaranews.com/berita/3933378/bi-dan-tpid-ntb-pelajari-inovasi-tasikmalaya-kendalikan-inflasi",
      "title": "BI dan TPID NTB pelajari inovasi Tasikmalaya kendalikan inflasi",
      "source": "ANTARA News",
      "date": "26 Jan 2024",
      "snippet": "Beberapa program tersebut, di antaranya pengembangan terpadu agribisnis khususnya untuk komoditas padi organik, telur ayam ras dan cabai melalui...",
      "thumbnail": "https://serpapi.com/searches/66432a55defa134ce756fb47/images/65153d8e15bd81304b168e489efb983d10d3c2dcadca7d49d178baecc5660131.jpeg"
    },
    {
      "position": 4,
      "link": "https://tugubandung.id/beras-salah-satu-faktor-penyumbang-inflasi-di-priangan-timur-bi-tasikmalaya-ajak-bijak-berbelanja/",
      "title": "Beras Salah Satu Faktor Penyumbang Inflasi di Priangan Timur, BI Tasikmalaya Ajak Bijak Berbelanja",
      "source": "tugubandung.id",
      "date": "1 bulan lalu",
      "snippet": "Beras Salah Satu Faktor Penyumbang Inflasi di Priangan Timur, BI Tasikmalaya Ajak Bijak Berbelanja ... KOTA TASIKMALAYA, (TUGU BANDUNG.ID).- Bulan...",
      "thumbnail": "https://serpapi.com/searches/66432a55defa134ce756fb47/images/65153d8e15bd8130b09e2270504df88b805c849a9d8563c3b1b1e4ed385321bf.jpeg"
    },
    {
      "position": 5,
      "link": "https://www.ayobandung.com/netizen/7912112072/inflasi-ramadhan-vs-keberkahannya-di-tasikmalaya",
      "title": "Inflasi Ramadhan vs Keberkahannya di Tasikmalaya - Ayo Bandung",
      "source": "Ayo Bandung",
      "date": "10 Mar 2024",
      "snippet": "BPS Kota Tasikmalaya melaporkan inflasi Kota Tasikmalaya sebesar 0,71 persen. Angka ini jauh naik dibandingkan Januari 2024.",
      "thumbnail": "https://serpapi.com/searches/66432a55defa134ce756fb47/images/65153d8e15bd8130e40fea86cd67e224ee4aa7585ebcf7fbd1abb4da4d879b56.jpeg"
    }
  ]
}
